tealinspector/__init__.py
tealinspector/cli.py
tealinspector/main.py
tealinspector-0.1.0.dist-info/LICENSE
tealinspector-0.1.0.dist-info/METADATA
tealinspector-0.1.0.dist-info/WHEEL
tealinspector-0.1.0.dist-info/entry_points.txt
tealinspector-0.1.0.dist-info/top_level.txt
tealinspector-0.1.0.dist-info/RECORD
